[
  {
    "id": "cov-internship",
    "title": "City of Vernon IT Internship",
    "description": "I am currently an IT intern for the City of Vernon. ",
    "bannerImage": "IT-Logo.jpg",
    "additionalImages": [
    ],
    "links": [
      {
        "name": "City of Vernon Website",
        "url": "https://www.cityofvernon.org/"
      }
    ],
    "date": "March 2023 - Present",
    "skills": [
      "Helpdesk",
      "Azure",
      "Typescript",
      "CSS",
      "A/B Testing"
    ]
  },
  {
    "id": "arl",
    "title": "Army Research Lab",
    "description": "COMING SOON",
    "bannerImage": "Web-Development.jpg",
    "additionalImages": [
    ],
    "links": [
      {
        "name": "Kojo article explanation",
        "url": "https://intercom.help/use-kojo/en/articles/6565012-intelligent-order-acknowledgments"
      }
    ],
    "date": "Fall 2022 - Spring 2023",
    "skills": [
      "Python",
      "Pandas",
      "Typescript",
      "GraphQL",
      "Postgres",
      "CSS",
      "Azure",
      "OCR"
    ]
  },
  {
    "id": "api",
    "title": "Weather App",
    "description": "The Weather App is a web application that provides real-time weather information for locations around the world. It allows users to check the current weather conditions, temperature, and more. The app is built using React.js and utilizes the OpenWeatherMap API to fetch weather data. ",
    "bannerImage": "WeatherApp.png",
    "additionalImages": [
      "WeatherApp.png"
    ],
    "links": [
      {
        "name": "NYT Books API",
        "url": "https://medium.com/kojo-engineering/rebranding-to-kojo-4ad8d8660e5d"
      },
      {
        "name": "Weather App",
        "url": "https://www.prnewswire.com/news-releases/construction-procurement-platform-agora-announces-rebrand-to-kojo-expands-into-all-major-trades-301552428.html"

      }
    ],
    "date": "April 2022",
    "skills": [
      "React",
      "Node.js",
      "Express.js",
      "HTML/CSS",
      "Javascript",
      "OpenWeatherMap API",
      "NYT Books API",
      "MongoDB"
    ]
  },
  {
    "id": "kojo-deliveries-v2",
    "title": "COMING SOON",
    "description": "COMING SOON",
    "bannerImage": "API-Logo.png",
    "additionalImages": [

    ],
    "links": [
      {
        "name": "Kojo Website",
        "url": "https://www.usekojo.com/"
      }
    ],
    "date": "Q3 & Q4 2021",
    "skills": [
      "React Native",
      "Node.js",
      "Javascript",
      "Typescript",
      "GraphQL",
      "Postgres",
      "AWS",
      "S3"
    ]
  },
  {
    "id": "microsoft-internship",
    "title": "COMING SOON",
    "description": "COMING SOON",
    "bannerImage": "Cloud-Pic.jpg",
    "additionalImages": [
    ],
    "links": [
      {
        "name": "Microsoft Website",
        "url": "https://www.microsoft.com/en-us/"
      }
    ],
    "date": "Summer 2017",
    "skills": [
      "Node.js",
      "Javascript",
      "Botbuilder SDK",
      "Azure Web Services",
      "Azure Table Storage"
    ]
  },
  {
    "id": "small projects",
    "title": "Temperature Converter",
    "description": "Temperature Converter: This is a web application that allows users to convert temperatures between Celsius, Fahrenheit, and Kelvin. ",
    "bannerImage": "TempConvert.png",
    "additionalImages": [
      "TempConvert.png"
    ],
    "links": [
      {
        "name": "Side Projects",
        "url": "https://www.microsoft.com/en-us/"
      }
    ],
    "date": "Summer 2023",
    "skills": [
      "Node.js",
      "Javascript",
      "BootStrap",
      "HTML/CSS",
      "JQuery"
    ]
  }
]
